{"total": {"lines":{"total":378,"covered":372,"skipped":0,"pct":98.41},"statements":{"total":382,"covered":376,"skipped":0,"pct":98.42},"functions":{"total":87,"covered":87,"skipped":0,"pct":100},"branches":{"total":333,"covered":295,"skipped":0,"pct":88.58},"branchesTrue":{"total":0,"covered":0,"skipped":0,"pct":100}}
,"E:\\projects\\kit-functions-sdk\\__test__\\constants.js": {"lines":{"total":4,"covered":4,"skipped":0,"pct":100},"functions":{"total":0,"covered":0,"skipped":0,"pct":100},"statements":{"total":4,"covered":4,"skipped":0,"pct":100},"branches":{"total":0,"covered":0,"skipped":0,"pct":100}}
,"E:\\projects\\kit-functions-sdk\\__test__\\context.js": {"lines":{"total":10,"covered":10,"skipped":0,"pct":100},"functions":{"total":0,"covered":0,"skipped":0,"pct":100},"statements":{"total":10,"covered":10,"skipped":0,"pct":100},"branches":{"total":0,"covered":0,"skipped":0,"pct":100}}
,"E:\\projects\\kit-functions-sdk\\dist\\Api.js": {"lines":{"total":22,"covered":22,"skipped":0,"pct":100},"functions":{"total":4,"covered":4,"skipped":0,"pct":100},"statements":{"total":22,"covered":22,"skipped":0,"pct":100},"branches":{"total":7,"covered":6,"skipped":0,"pct":85.71}}
,"E:\\projects\\kit-functions-sdk\\dist\\Avatar.js": {"lines":{"total":26,"covered":26,"skipped":0,"pct":100},"functions":{"total":6,"covered":6,"skipped":0,"pct":100},"statements":{"total":26,"covered":26,"skipped":0,"pct":100},"branches":{"total":16,"covered":13,"skipped":0,"pct":81.25}}
,"E:\\projects\\kit-functions-sdk\\dist\\DB.js": {"lines":{"total":37,"covered":37,"skipped":0,"pct":100},"functions":{"total":17,"covered":17,"skipped":0,"pct":100},"statements":{"total":39,"covered":39,"skipped":0,"pct":100},"branches":{"total":68,"covered":59,"skipped":0,"pct":86.76}}
,"E:\\projects\\kit-functions-sdk\\dist\\Message.js": {"lines":{"total":10,"covered":10,"skipped":0,"pct":100},"functions":{"total":1,"covered":1,"skipped":0,"pct":100},"statements":{"total":10,"covered":10,"skipped":0,"pct":100},"branches":{"total":1,"covered":1,"skipped":0,"pct":100}}
,"E:\\projects\\kit-functions-sdk\\dist\\index.js": {"lines":{"total":247,"covered":243,"skipped":0,"pct":98.38},"functions":{"total":54,"covered":54,"skipped":0,"pct":100},"statements":{"total":249,"covered":245,"skipped":0,"pct":98.39},"branches":{"total":233,"covered":209,"skipped":0,"pct":89.69}}
,"E:\\projects\\kit-functions-sdk\\dist\\utils.js": {"lines":{"total":22,"covered":20,"skipped":0,"pct":90.9},"functions":{"total":5,"covered":5,"skipped":0,"pct":100},"statements":{"total":22,"covered":20,"skipped":0,"pct":90.9},"branches":{"total":8,"covered":7,"skipped":0,"pct":87.5}}
}
